ezmsg/core/__init__.py
ezmsg/core/__main__.py
ezmsg/core/addressable.py
ezmsg/core/backend.py
ezmsg/core/backendprocess.py
ezmsg/core/backpressure.py
ezmsg/core/collection.py
ezmsg/core/command.py
ezmsg/core/component.py
ezmsg/core/dag.py
ezmsg/core/graphcontext.py
ezmsg/core/graphserver.py
ezmsg/core/message.py
ezmsg/core/messagecache.py
ezmsg/core/messagemarshal.py
ezmsg/core/netprotocol.py
ezmsg/core/pubclient.py
ezmsg/core/server.py
ezmsg/core/settings.py
ezmsg/core/shmserver.py
ezmsg/core/state.py
ezmsg/core/stream.py
ezmsg/core/subclient.py
ezmsg/core/unit.py
ezmsg/core/util.py
ezmsg/util/__init__.py
ezmsg/util/debuglog.py
ezmsg/util/gen_to_unit.py
ezmsg/util/generator.py
ezmsg/util/messagecodec.py
ezmsg/util/messagegate.py
ezmsg/util/messagelogger.py
ezmsg/util/messagequeue.py
ezmsg/util/messagereplay.py
ezmsg/util/perf_test.py
ezmsg/util/rate.py
ezmsg/util/terminate.py
ezmsg/util/messages/__init__.py
ezmsg/util/messages/axisarray.py
ezmsg/util/messages/chunker.py
ezmsg/util/messages/key.py
ezmsg/util/messages/modify.py
ezmsg/util/messages/util.py
ezmsg-3.6.2.dist-info/METADATA
ezmsg-3.6.2.dist-info/WHEEL
ezmsg-3.6.2.dist-info/entry_points.txt
ezmsg-3.6.2.dist-info/licenses/LICENSE
ezmsg-3.6.2.dist-info/RECORD
