Metadata-Version: 2.4
Name: ezmsg
Version: 3.6.2
Summary: A simple DAG-based computation model
Author-email: Griffin Milsap <griffin.milsap@gmail.com>, Preston Peranich <pperanich@gmail.com>, Chadwick Boulay <chadwick.boulay@gmail.com>
License: MIT License
License-File: LICENSE
Classifier: Operating System :: OS Independent
Classifier: Programming Language :: Python :: 3
Requires-Python: >=3.8
Requires-Dist: typing-extensions>=4.9.0
Provides-Extra: axisarray
Requires-Dist: numpy>=1.24.4; extra == 'axisarray'
Provides-Extra: docs
Requires-Dist: ezmsg-sigproc>=1.2.3; extra == 'docs'
Requires-Dist: sphinx-rtd-theme==2.0.0; extra == 'docs'
Requires-Dist: sphinx<=7.2; extra == 'docs'
Provides-Extra: test
Requires-Dist: flake8>=5.0.4; extra == 'test'
Requires-Dist: numpy>=1.24.4; extra == 'test'
Requires-Dist: pytest-asyncio>=0.23.8; extra == 'test'
Requires-Dist: pytest-cov>=5.0.0; extra == 'test'
Requires-Dist: pytest>=7.0.0; extra == 'test'
Requires-Dist: xarray>=2023.1.0; (python_version < '3.13') and extra == 'test'
